{
    "id": "global-config",
    "created": "2025-01-01T00:00:00Z",
    "updated": "2025-01-01T01:00:00Z",
    "websiteId": "website-id-123",
    "global": {
        "layout": {
            "name": "Revamp Marketing",
            "themeColor": "#ffffff",
            "baseUrl": "https://www.revampmarketing.net",
            "defaultTitle": "Revamp Marketing | Data-Driven Solutions for Business Growth",
            "defaultDescription": "At Revamp Marketing, we specialize in SEO, ads, social media, web design, and AI-powered solutions to transform your business. Elevate your brand and maximize your success with our expertise.",
            "keywords": [
                "SEO",
                "digital marketing",
                "AI solutions",
                "business growth",
                "targeted ads",
                "social media"
            ]
        },
        "html": {
            "className": "scroll-smooth",
            "lang": "en"
        },
        "body": {
            "className": "md:overflow-visible"
        },
        "analytics": {
            "google": {
                "id": "google-analytics",
                "src": "https://www.googletagmanager.com/gtag/js?id=YOUR_ANALYTICS_ID",
                "script": "window.dataLayer = window.dataLayer || []; function gtag(){dataLayer.push(arguments);} gtag('js', new Date()); gtag('config', 'YOUR_ANALYTICS_ID');"
            }
        },
        "navbar": {
            "logo": {
                "mobile": {
                    "src": "https://cdn.revampmarketing.net/logo-small.png",
                    "alt": "Revamp Marketing Logo",
                    "width": 50,
                    "height": 50
                },
                "desktop": {
                    "src": "https://cdn.revampmarketing.net/logo-large-light.svg",
                    "alt": "Revamp Marketing Logo",
                    "width": 250,
                    "height": 100
                }
            },
            "navigation": [
                {
                    "id": 1,
                    "label": "Services",
                    "items": [
                        {
                            "id": 1,
                            "label": "Website Development",
                            "path": "/services/website-development"
                        },
                        {
                            "id": 2,
                            "label": "SEO Management",
                            "path": "/services/seo"
                        },
                        {
                            "id": 3,
                            "label": "Social Media Management",
                            "path": "/services/social-media"
                        }
                    ]
                },
                {
                    "id": 2,
                    "label": "Resources",
                    "items": [
                        {
                            "id": 1,
                            "label": "Blog",
                            "path": "/blog"
                        },
                        {
                            "id": 2,
                            "label": "Case Studies",
                            "path": "/resources/case-studies"
                        },
                        {
                            "id": 3,
                            "label": "FAQs",
                            "path": "/resources/faqs"
                        }
                    ]
                },
                {
                    "id": 3,
                    "label": "Pricing",
                    "path": "/pricing"
                },
                {
                    "id": 4,
                    "label": "Contact",
                    "path": "/contact"
                }
            ],
            "ctaButton": {
                "text": "Get Started",
                "link": "/get-started",
                "analytics": {
                    "eventLabel": "Get Started",
                    "eventCategory": "Navbar Interaction",
                    "eventAction": "link_click",
                    "eventValue": "Get Started"
                }
            },
            "settings": {
                "styles": {
                    "header": {
                        "position": "sticky",
                        "top": "top-4",
                        "zIndex": "z-50",
                        "border": "border",
                        "padding": "py-2",
                        "shadow": "shadow-lg",
                        "rounded": "rounded-lg",
                        "margin": "mx-4 md:mx-24",
                        "background": "bg-white"
                    },
                    "nav": {
                        "maxWidth": "max-w-screen-xl",
                        "centered": "mx-auto"
                    },
                    "container": {
                        "layout": "flex items-center justify-between",
                        "padding": "py-5 px-6",
                        "rounded": "rounded-lg"
                    }
                },
                "desktop": {
                    "styles": {
                        "list": {
                            "display": "hidden lg:flex",
                            "alignment": "items-center justify-end",
                            "spacing": "space-x-8"
                        },
                        "listItem": {
                            "position": "relative",
                            "group": "group"
                        },
                        "title": {
                            "text": "text-md text-gray-800",
                            "cursor": "cursor-pointer",
                            "inline": "inline-block relative",
                            "underline": "after:content-[''] after:absolute after:left-0 after:right-0 after:bottom-[-4px] after:h-[2px] after:bg-[#18CB96] after:transition-all after:duration-300 after:ease-in-out after:w-0 group-hover:after:w-full"
                        },
                        "dropdown": {
                            "container": "absolute left-0 top-full mt-2 bg-white shadow-md rounded-md p-3 w-60 z-10",
                            "transition": "transition-all duration-300 opacity-0 invisible group-hover:opacity-100 group-hover:visible"
                        },
                        "dropdownItem": {
                            "padding": "p-2",
                            "alignment": "flex items-center",
                            "text": "text-gray-700",
                            "cursor": "cursor-pointer",
                            "rounded": "rounded-md",
                            "hover": "hover:bg-gray-100"
                        },
                        "button": {
                            "text": "text-white",
                            "background": "bg-primary hover:bg-primary-light",
                            "rounded": "rounded-md",
                            "padding": "px-6 py-3",
                            "cursor": "cursor-pointer",
                            "transition": "transition-colors duration-200"
                        }
                    }
                }
            },
            "mobile": {
                "toggleButton": {
                    "color": "text-gray-500 hover:text-gray-800",
                    "transition": "transition-colors duration-200",
                    "layout": "block lg:hidden"
                },
                "menuContainer": {
                    "position": "fixed inset-0 top-0 bg-white lg:hidden",
                    "transition": "transition-transform duration-300",
                    "layout": "flex flex-col h-full"
                },
                "menuContent": {
                    "layout": "flex-1 overflow-y-auto px-6 py-8"
                },
                "menuVisible": {
                    "transform": "translate-x-0"
                },
                "menuHidden": {
                    "transform": "translate-x-full"
                },
                "header": {
                    "layout": "flex items-center justify-between",
                    "padding": "p-6",
                    "border": "border-b"
                },
                "itemGroup": {
                    "container": "mb-6",
                    "title": "text-lg font-semibold text-gray-800 mb-4",
                    "itemList": "space-y-3 pl-4"
                },
                "listItem": {
                    "text": "p-3 text-gray-700",
                    "hover": "hover:bg-gray-100 active:bg-gray-200",
                    "rounded": "rounded-md",
                    "transition": "transition-colors duration-200"
                },
                "navButton": {
                    "layout": "block w-full text-center",
                    "text": "text-white bg-primary hover:bg-primary-light active:bg-primary-dark",
                    "rounded": "rounded-md",
                    "padding": "px-6 py-3",
                    "transition": "transition-colors duration-200"
                },
                "ctaButtonContainer": {
                    "marginTop": "mt-8"
                }
            }
        },
        "footer": {
            "navigation": [
                {
                    "id": 1,
                    "label": "Services",
                    "items": [
                        {
                            "id": 1,
                            "label": "Website Development",
                            "path": "/services/website-development"
                        },
                        {
                            "id": 2,
                            "label": "SEO Management",
                            "path": "/services/seo"
                        },
                        {
                            "id": 3,
                            "label": "Social Media Management",
                            "path": "/services/social-media"
                        }
                    ]
                },
                {
                    "id": 2,
                    "label": "Resources",
                    "items": [
                        {
                            "id": 1,
                            "label": "About",
                            "path": "/about"
                        },
                        {
                            "id": 2,
                            "label": "Blog",
                            "path": "/blog"
                        },
                        {
                            "id": 3,
                            "label": "FAQs",
                            "path": "/resources/faqs"
                        }
                    ]
                },
                {
                    "id": 3,
                    "label": "Additional Resources",
                    "items": [
                        {
                            "id": 1,
                            "label": "Pricing",
                            "path": "/pricing"
                        },
                        {
                            "id": 2,
                            "label": "Contact",
                            "path": "/contact"
                        }
                    ]
                }
            ],
            "address": {
                "line1": "123 Revamp St",
                "line2": "Marketing City, NY 12345",
                "country": "USA"
            },
            "social": [
                {
                    "key": "facebook",
                    "value": "https://facebook.com"
                },
                {
                    "key": "twitter",
                    "value": "https://twitter.com"
                },
                {
                    "key": "linkedin",
                    "value": "https://linkedin.com"
                }
            ],
            "copyright": "© 2025 RevampMarketing. All rights reserved.",
            "links": [
                {
                    "label": "Privacy Policy",
                    "path": "/privacy-policy"
                },
                {
                    "label": "Terms",
                    "path": "/terms"
                }
            ]
        }
    }
}